odoo/addons/l10n_es_account_banking_sepa_fsdd/README.rst
odoo/addons/l10n_es_account_banking_sepa_fsdd/__init__.py
odoo/addons/l10n_es_account_banking_sepa_fsdd/__manifest__.py
odoo/addons/l10n_es_account_banking_sepa_fsdd/i18n/ca.po
odoo/addons/l10n_es_account_banking_sepa_fsdd/i18n/es.po
odoo/addons/l10n_es_account_banking_sepa_fsdd/i18n/fr.po
odoo/addons/l10n_es_account_banking_sepa_fsdd/i18n/l10n_es_account_banking_sepa_fsdd.pot
odoo/addons/l10n_es_account_banking_sepa_fsdd/i18n/nl.po
odoo/addons/l10n_es_account_banking_sepa_fsdd/i18n/pt_BR.po
odoo/addons/l10n_es_account_banking_sepa_fsdd/i18n/sl.po
odoo/addons/l10n_es_account_banking_sepa_fsdd/models/__init__.py
odoo/addons/l10n_es_account_banking_sepa_fsdd/models/account_payment_mode.py
odoo/addons/l10n_es_account_banking_sepa_fsdd/models/account_payment_order.py
odoo/addons/l10n_es_account_banking_sepa_fsdd/readme/CONFIGURE.md
odoo/addons/l10n_es_account_banking_sepa_fsdd/readme/CONTRIBUTORS.md
odoo/addons/l10n_es_account_banking_sepa_fsdd/readme/DESCRIPTION.md
odoo/addons/l10n_es_account_banking_sepa_fsdd/readme/INSTALL.md
odoo/addons/l10n_es_account_banking_sepa_fsdd/static/description/icon.png
odoo/addons/l10n_es_account_banking_sepa_fsdd/static/description/index.html
odoo/addons/l10n_es_account_banking_sepa_fsdd/tests/__init__.py
odoo/addons/l10n_es_account_banking_sepa_fsdd/tests/test_l10n_es_account_banking_sepa_fsdd.py
odoo/addons/l10n_es_account_banking_sepa_fsdd/views/payment_mode_view.xml
odoo_addon_l10n_es_account_banking_sepa_fsdd-18.0.1.0.0.2.dist-info/METADATA
odoo_addon_l10n_es_account_banking_sepa_fsdd-18.0.1.0.0.2.dist-info/WHEEL
odoo_addon_l10n_es_account_banking_sepa_fsdd-18.0.1.0.0.2.dist-info/top_level.txt
odoo_addon_l10n_es_account_banking_sepa_fsdd-18.0.1.0.0.2.dist-info/RECORD
