Metadata-Version: 2.1
Name: odoo-addon-l10n_es_account_banking_sepa_fsdd
Version: 18.0.1.0.0.2
Requires-Python: >=3.10
Requires-Dist: odoo-addon-account_banking_sepa_direct_debit==18.0.*
Requires-Dist: odoo==18.0.*
Summary: =?utf-8?q?Account_Banking_Sepa_-_FSDD_=28Anticipos_de_cr=C3=A9dito=29?=
Home-page: https://github.com/OCA/l10n-spain
License: AGPL-3
Author: Tecnativa, Odoo Community Association (OCA)
Author-email: support@odoo-community.org
Classifier: Programming Language :: Python
Classifier: Framework :: Odoo
Classifier: Framework :: Odoo :: 18.0
Classifier: License :: OSI Approved :: GNU Affero General Public License v3
